molharbor/__init__.py
molharbor/checker.py
molharbor/data.py
molharbor/enums.py
molharbor/exceptions.py
molharbor/utils.py
molharbor-0.1.5.dist-info/METADATA
molharbor-0.1.5.dist-info/WHEEL
molharbor-0.1.5.dist-info/licenses/LICENSE
molharbor-0.1.5.dist-info/RECORD
