Metadata-Version: 2.4
Name: molharbor
Version: 0.1.5
Summary:  unofficial python wrapper for MolPort API
Project-URL: homepage, https://github.com/asiomchen/molharbor
Project-URL: repository, https://github.com/asiomchen/molharbor
Author-email: Anton Siomchen <41703271+asiomchen@users.noreply.github.com>
License: Apache-2.0
License-File: LICENSE
Keywords: chemistry,molport,vhts
Classifier: Development Status :: 3 - Alpha
Classifier: Intended Audience :: Science/Research
Classifier: License :: OSI Approved :: Apache Software License
Classifier: Programming Language :: Python :: 3 :: Only
Classifier: Programming Language :: Python :: 3.9
Classifier: Programming Language :: Python :: 3.10
Classifier: Programming Language :: Python :: 3.11
Classifier: Programming Language :: Python :: 3.12
Classifier: Topic :: Scientific/Engineering
Classifier: Topic :: Utilities
Requires-Python: >=3.9
Requires-Dist: cloudscraper>=1.2.71
Requires-Dist: numpy>=1.26.4
Requires-Dist: pandas>=2.2.2
Requires-Dist: pydantic>=2.7.1
Requires-Dist: requests>=2.31.0
Requires-Dist: tqdm>=4.66.4
